[
  {
    "id": "osm-way-1425376104",
    "name": "Бели Дунав - Връбница",
    "latitude": 42.7363216,
    "longitude": 23.2918606,
    "category": "buffer",
    "capacity": 128,
    "fee": true,
    "charge": null,
    "operator": "Център за градска мобилност",
    "parkRide": true,
    "openingHours": null,
    "website": null,
    "phone": null,
    "maxheight": null,
    "surface": null
  },
  {
    "id": "osm-way-1425376105",
    "name": "Бели Дунав - Надежда",
    "latitude": 42.7336737,
    "longitude": 23.2947967,
    "category": "buffer",
    "capacity": 350,
    "fee": true,
    "charge": null,
    "operator": "Център за градска мобилност",
    "parkRide": true,
    "openingHours": null,
    "website": null,
    "phone": null,
    "maxheight": null,
    "surface": null
  },
  {
    "id": "osm-node-11013588399",
    "name": "Буферен паркинг „Цариградско шосе“",
    "latitude": 42.6492465,
    "longitude": 23.3944684,
    "category": "buffer",
    "capacity": null,
    "fee": true,
    "charge": null,
    "operator": "Център за градска мобилност",
    "parkRide": true,
    "openingHours": "05:00-24:00",
    "website": null,
    "phone": null,
    "maxheight": 2.5,
    "surface": null
  },
  {
    "id": "osm-way-397987677",
    "name": "Метростанция Цариградско Шосе",
    "latitude": 42.6486116,
    "longitude": 23.39493,
    "category": "buffer",
    "capacity": 1300,
    "fee": true,
    "charge": null,
    "operator": null,
    "parkRide": true,
    "openingHours": null,
    "website": null,
    "phone": null,
    "maxheight": null,
    "surface": null
  },
  {
    "id": "osm-way-437661586",
    "name": "Паркинг „Джеймс Баучер“",
    "latitude": 42.6690488,
    "longitude": 23.319571,
    "category": "underground",
    "capacity": 577,
    "fee": true,
    "charge": null,
    "operator": null,
    "parkRide": false,
    "openingHours": null,
    "website": null,
    "phone": null,
    "maxheight": null,
    "surface": null
  },
  {
    "id": "osm-way-1372410774",
    "name": "Паркинг Витоша",
    "latitude": 42.6808166,
    "longitude": 23.3125561,
    "category": "underground",
    "capacity": 400,
    "fee": true,
    "charge": null,
    "operator": "Център за градска мобилност",
    "parkRide": false,
    "openingHours": null,
    "website": null,
    "phone": null,
    "maxheight": null,
    "surface": null
  },
  {
    "id": "osm-way-1276217517",
    "name": "Паркинг НДК",
    "latitude": 42.684638,
    "longitude": 23.3201645,
    "category": "underground",
    "capacity": null,
    "fee": true,
    "charge": null,
    "operator": null,
    "parkRide": false,
    "openingHours": null,
    "website": null,
    "phone": null,
    "maxheight": 2,
    "surface": "concrete"
  },
  {
    "id": "osm-way-1289582954",
    "name": "Паркинг стадион Васил Левски",
    "latitude": 42.6855581,
    "longitude": 23.3325698,
    "category": "underground",
    "capacity": 193,
    "fee": true,
    "charge": null,
    "operator": "Център за градска мобилност",
    "parkRide": false,
    "openingHours": "Mo-Su 05:00-24:00",
    "website": "https://www.sofiatraffic.bg/bg/transport/parkirane-v-bufernite-parkingi/p/1",
    "phone": null,
    "maxheight": null,
    "surface": null
  },
  {
    "id": "osm-node-2375388578",
    "name": "Mall of Sofia Parking",
    "latitude": 42.6979851,
    "longitude": 23.3081856,
    "category": "underground",
    "capacity": 600,
    "fee": true,
    "charge": null,
    "operator": null,
    "parkRide": false,
    "openingHours": null,
    "website": null,
    "phone": null,
    "maxheight": null,
    "surface": null
  },
  {
    "id": "osm-node-8750163259",
    "name": "PARKING CENTRAL",
    "latitude": 42.6983567,
    "longitude": 23.3190816,
    "category": "underground",
    "capacity": 100,
    "fee": true,
    "charge": "2 BGN per hour",
    "operator": "Parking Central",
    "parkRide": false,
    "openingHours": "Mo-Su 00:00-24:00",
    "website": null,
    "phone": "+359 89 459 0038",
    "maxheight": null,
    "surface": "asphalt"
  },
  {
    "id": "osm-way-463476328",
    "name": "Aeroport T1 Sofia",
    "latitude": 42.688593,
    "longitude": 23.4021293,
    "category": "airport",
    "capacity": null,
    "fee": true,
    "charge": null,
    "operator": null,
    "parkRide": false,
    "openingHours": null,
    "website": null,
    "phone": null,
    "maxheight": null,
    "surface": "asphalt"
  },
  {
    "id": "osm-way-1011975001",
    "name": "Parking Airport Sofia",
    "latitude": 42.6851324,
    "longitude": 23.4039529,
    "category": "airport",
    "capacity": null,
    "fee": true,
    "charge": null,
    "operator": null,
    "parkRide": false,
    "openingHours": null,
    "website": null,
    "phone": null,
    "maxheight": null,
    "surface": null
  },
  {
    "id": "osm-way-715737371",
    "name": "Аквила В ЕООД паркинг",
    "latitude": 42.6988228,
    "longitude": 23.3285168,
    "category": "surface",
    "capacity": 25,
    "fee": true,
    "charge": "2 лв./hour;170 лв./month",
    "operator": "Аквила В ЕООД",
    "parkRide": false,
    "openingHours": "Mo-Fr 08:30-19:00",
    "website": null,
    "phone": null,
    "maxheight": null,
    "surface": "asphalt"
  },
  {
    "id": "osm-way-1331589374",
    "name": "Блутауър ЕООД паркинг",
    "latitude": 42.6444661,
    "longitude": 23.3437925,
    "category": "surface",
    "capacity": null,
    "fee": true,
    "charge": null,
    "operator": "Блутауър ЕООД",
    "parkRide": false,
    "openingHours": null,
    "website": null,
    "phone": null,
    "maxheight": null,
    "surface": null
  },
  {
    "id": "osm-node-2934031298",
    "name": "Гладстон",
    "latitude": 42.6911812,
    "longitude": 23.3227316,
    "category": "surface",
    "capacity": null,
    "fee": true,
    "charge": null,
    "operator": null,
    "parkRide": false,
    "openingHours": null,
    "website": null,
    "phone": null,
    "maxheight": null,
    "surface": null
  },
  {
    "id": "osm-way-531473091",
    "name": "Кино Арена България ЕООД паркинг",
    "latitude": 42.625142,
    "longitude": 23.3767665,
    "category": "surface",
    "capacity": null,
    "fee": true,
    "charge": null,
    "operator": "Кино Арена България ЕООД",
    "parkRide": false,
    "openingHours": null,
    "website": null,
    "phone": null,
    "maxheight": null,
    "surface": "asphalt"
  },
  {
    "id": "osm-way-1303469680",
    "name": "Паркинг \"Западен парк\"",
    "latitude": 42.7155259,
    "longitude": 23.2788479,
    "category": "surface",
    "capacity": 240,
    "fee": true,
    "charge": null,
    "operator": null,
    "parkRide": false,
    "openingHours": null,
    "website": null,
    "phone": null,
    "maxheight": null,
    "surface": "asphalt"
  },
  {
    "id": "osm-way-588023390",
    "name": "Паркинг А.2",
    "latitude": 42.6904584,
    "longitude": 23.2936126,
    "category": "surface",
    "capacity": null,
    "fee": true,
    "charge": null,
    "operator": null,
    "parkRide": false,
    "openingHours": null,
    "website": null,
    "phone": null,
    "maxheight": null,
    "surface": null
  },
  {
    "id": "osm-way-553519253",
    "name": "Паркинг А.3",
    "latitude": 42.6903999,
    "longitude": 23.2946952,
    "category": "surface",
    "capacity": null,
    "fee": true,
    "charge": null,
    "operator": null,
    "parkRide": false,
    "openingHours": null,
    "website": null,
    "phone": null,
    "maxheight": null,
    "surface": null
  },
  {
    "id": "osm-way-550270843",
    "name": "УБ \"Майчин дом\" паркинг",
    "latitude": 42.6841161,
    "longitude": 23.3114232,
    "category": "surface",
    "capacity": null,
    "fee": true,
    "charge": null,
    "operator": "УБ \"Майчин дом\"",
    "parkRide": false,
    "openingHours": null,
    "website": null,
    "phone": null,
    "maxheight": null,
    "surface": null
  },
  {
    "id": "osm-way-581713060",
    "name": "III База",
    "latitude": 42.7425578,
    "longitude": 23.3096163,
    "category": "surface",
    "capacity": 72,
    "fee": true,
    "charge": null,
    "operator": null,
    "parkRide": false,
    "openingHours": null,
    "website": null,
    "phone": null,
    "maxheight": null,
    "surface": "asphalt"
  },
  {
    "id": "osm-way-303864752",
    "name": "Ivailo паркинг",
    "latitude": 42.6986426,
    "longitude": 23.3282282,
    "category": "surface",
    "capacity": 60,
    "fee": true,
    "charge": "190 лв./month",
    "operator": "Ivailo",
    "parkRide": false,
    "openingHours": "Mo-Fr 08:00-20:00",
    "website": null,
    "phone": "+359 87 824 2724",
    "maxheight": null,
    "surface": "asphalt"
  },
  {
    "id": "osm-way-463636983",
    "name": "P5",
    "latitude": 42.6875453,
    "longitude": 23.4141743,
    "category": "surface",
    "capacity": null,
    "fee": true,
    "charge": null,
    "operator": null,
    "parkRide": false,
    "openingHours": null,
    "website": null,
    "phone": null,
    "maxheight": null,
    "surface": null
  },
  {
    "id": "osm-way-469539541",
    "name": "Park & Fly",
    "latitude": 42.6894161,
    "longitude": 23.3900211,
    "category": "surface",
    "capacity": null,
    "fee": true,
    "charge": null,
    "operator": null,
    "parkRide": false,
    "openingHours": null,
    "website": null,
    "phone": null,
    "maxheight": null,
    "surface": null
  },
  {
    "id": "osm-way-1411060680",
    "name": "Sofia Municipality паркинг",
    "latitude": 42.6678479,
    "longitude": 23.3190888,
    "category": "surface",
    "capacity": 36,
    "fee": true,
    "charge": null,
    "operator": "Sofia Municipality",
    "parkRide": false,
    "openingHours": null,
    "website": null,
    "phone": null,
    "maxheight": null,
    "surface": "asphalt"
  },
  {
    "id": "osm-way-146881724",
    "name": "Паркинг А.1",
    "latitude": 42.6907652,
    "longitude": 23.2941041,
    "category": "commercial",
    "capacity": 100,
    "fee": true,
    "charge": null,
    "operator": "БЦ Сердика",
    "parkRide": false,
    "openingHours": null,
    "website": null,
    "phone": null,
    "maxheight": null,
    "surface": null
  },
  {
    "id": "osm-way-146881723",
    "name": "Паркинг Б",
    "latitude": 42.6915218,
    "longitude": 23.2950678,
    "category": "commercial",
    "capacity": 100,
    "fee": true,
    "charge": null,
    "operator": "БЦ Сердика",
    "parkRide": false,
    "openingHours": null,
    "website": null,
    "phone": null,
    "maxheight": null,
    "surface": null
  },
  {
    "id": "osm-way-876192399",
    "name": "Софиямед паркинг",
    "latitude": 42.7141461,
    "longitude": 23.2571244,
    "category": "commercial",
    "capacity": null,
    "fee": true,
    "charge": null,
    "operator": "Софиямед",
    "parkRide": false,
    "openingHours": null,
    "website": null,
    "phone": null,
    "maxheight": null,
    "surface": "asphalt"
  },
  {
    "id": "osm-way-550270828",
    "name": "УБ \"Майчин дом\" паркинг",
    "latitude": 42.6839555,
    "longitude": 23.3122236,
    "category": "commercial",
    "capacity": 40,
    "fee": true,
    "charge": null,
    "operator": "УБ \"Майчин дом\"",
    "parkRide": false,
    "openingHours": null,
    "website": null,
    "phone": null,
    "maxheight": null,
    "surface": null
  },
  {
    "id": "osm-way-1248801542",
    "name": "Billa паркинг",
    "latitude": 42.6585609,
    "longitude": 23.2719377,
    "category": "commercial",
    "capacity": 62,
    "fee": true,
    "charge": null,
    "operator": "Billa",
    "parkRide": false,
    "openingHours": null,
    "website": null,
    "phone": null,
    "maxheight": null,
    "surface": null
  },
  {
    "id": "osm-way-1103632919",
    "name": "Billa паркинг",
    "latitude": 42.6739759,
    "longitude": 23.3325714,
    "category": "commercial",
    "capacity": null,
    "fee": true,
    "charge": null,
    "operator": "Billa",
    "parkRide": false,
    "openingHours": null,
    "website": null,
    "phone": null,
    "maxheight": null,
    "surface": null
  },
  {
    "id": "osm-way-1103632921",
    "name": "Billa паркинг",
    "latitude": 42.6738708,
    "longitude": 23.3328006,
    "category": "commercial",
    "capacity": null,
    "fee": true,
    "charge": null,
    "operator": "Billa",
    "parkRide": false,
    "openingHours": null,
    "website": null,
    "phone": null,
    "maxheight": null,
    "surface": "paving_stones"
  },
  {
    "id": "osm-way-1103632922",
    "name": "Billa паркинг",
    "latitude": 42.6740293,
    "longitude": 23.3332189,
    "category": "commercial",
    "capacity": null,
    "fee": true,
    "charge": null,
    "operator": "Billa",
    "parkRide": false,
    "openingHours": null,
    "website": null,
    "phone": null,
    "maxheight": null,
    "surface": "paving_stones"
  },
  {
    "id": "osm-way-1443284213",
    "name": "Billa паркинг",
    "latitude": 42.673812,
    "longitude": 23.3329661,
    "category": "commercial",
    "capacity": null,
    "fee": true,
    "charge": null,
    "operator": "Billa",
    "parkRide": false,
    "openingHours": null,
    "website": null,
    "phone": null,
    "maxheight": null,
    "surface": "paving_stones"
  },
  {
    "id": "osm-way-691089047",
    "name": "Hotel Downtown паркинг",
    "latitude": 42.6865792,
    "longitude": 23.324818,
    "category": "commercial",
    "capacity": null,
    "fee": true,
    "charge": null,
    "operator": "Hotel Downtown",
    "parkRide": false,
    "openingHours": null,
    "website": null,
    "phone": null,
    "maxheight": null,
    "surface": null
  },
  {
    "id": "osm-way-147355055",
    "name": "I База",
    "latitude": 42.7403905,
    "longitude": 23.3147936,
    "category": "commercial",
    "capacity": 600,
    "fee": true,
    "charge": null,
    "operator": null,
    "parkRide": false,
    "openingHours": null,
    "website": null,
    "phone": null,
    "maxheight": null,
    "surface": "asphalt"
  },
  {
    "id": "osm-way-500062691",
    "name": "Kaufland паркинг",
    "latitude": 42.6705546,
    "longitude": 23.2731268,
    "category": "commercial",
    "capacity": null,
    "fee": true,
    "charge": "3.00 BGN",
    "operator": "Kaufland",
    "parkRide": false,
    "openingHours": null,
    "website": null,
    "phone": null,
    "maxheight": null,
    "surface": "asphalt"
  },
  {
    "id": "osm-way-378442943",
    "name": "OMV паркинг",
    "latitude": 42.7110163,
    "longitude": 23.2717114,
    "category": "commercial",
    "capacity": 9,
    "fee": true,
    "charge": null,
    "operator": "OMV",
    "parkRide": false,
    "openingHours": null,
    "website": null,
    "phone": null,
    "maxheight": null,
    "surface": "asphalt"
  },
  {
    "id": "osm-way-754049838",
    "name": "OMV паркинг",
    "latitude": 42.7107355,
    "longitude": 23.2721107,
    "category": "commercial",
    "capacity": 12,
    "fee": true,
    "charge": null,
    "operator": "OMV",
    "parkRide": false,
    "openingHours": null,
    "website": null,
    "phone": null,
    "maxheight": null,
    "surface": "asphalt"
  },
  {
    "id": "osm-way-114317213",
    "name": "the mall",
    "latitude": 42.6602861,
    "longitude": 23.3816635,
    "category": "commercial",
    "capacity": null,
    "fee": true,
    "charge": null,
    "operator": null,
    "parkRide": false,
    "openingHours": null,
    "website": null,
    "phone": null,
    "maxheight": null,
    "surface": null
  },
  {
    "id": "osm-relation-16078797",
    "name": "Наказателен паркинг Дружба",
    "latitude": 42.6673023,
    "longitude": 23.3922072,
    "category": "impound",
    "capacity": null,
    "fee": true,
    "charge": null,
    "operator": "Център за градска мобилност",
    "parkRide": false,
    "openingHours": null,
    "website": null,
    "phone": null,
    "maxheight": null,
    "surface": null
  },
  {
    "id": "osm-way-316489046",
    "name": "Наказателен паркинг Подуяне",
    "latitude": 42.6971816,
    "longitude": 23.3562513,
    "category": "impound",
    "capacity": null,
    "fee": true,
    "charge": null,
    "operator": "Център за градска мобилност",
    "parkRide": false,
    "openingHours": null,
    "website": null,
    "phone": null,
    "maxheight": null,
    "surface": null
  }
]